exitcode/__init__.py
exitcode/py.typed
exitcode-0.1.0.dist-info/LICENSE
exitcode-0.1.0.dist-info/METADATA
exitcode-0.1.0.dist-info/WHEEL
exitcode-0.1.0.dist-info/RECORD
