Metadata-Version: 2.1
Name: exitcode
Version: 0.1.0
Summary: Preferred system exit codes as defined by sysexits.h
Home-page: https://github.com/rumpelsepp/exitcode
License: MIT
Author: Stefan Tatschner
Author-email: stefan@rumpelsepp.org
Maintainer: Stefan Tatschner
Maintainer-email: stefan@rumpelsepp.org
Requires-Python: >=3.10
Classifier: License :: OSI Approved :: MIT License
Classifier: Operating System :: POSIX :: Linux
Classifier: Programming Language :: Python :: 3
Classifier: Programming Language :: Python :: 3.10
Classifier: Programming Language :: Python :: 3.11
Project-URL: Repository, https://github.com/rumpelsepp/exitcode
